<?xml version = '1.0' encoding = 'UTF-8'?>
<TableProxyOraclev11g class="oracle.dbtools.crest.model.design.storage.oracle.v11g.TableProxyOraclev11g" name="IFN_SUELOS" directorySegmentName="seg_0" id="5C9767F9-D969-BF4B-4736-B51421E89BE2">
<createdBy>Usuario</createdBy>
<createdTime>2017-04-03 21:48:46 UTC</createdTime>
<ownerDesignName>disenoCubo</ownerDesignName>
<schemaObject>3E48E386-25C0-F1B3-46F2-EE06203B5612</schemaObject>
<logging>YES</logging>
<partitionedRowMovement>DISABLE</partitionedRowMovement>
<segment>6596175D-74BA-BCC4-FC1C-8D5EF60F83B2</segment>
<tableSpace>23A7666B-255B-EDE8-9B57-201EAD136BD1</tableSpace>
<temporaryChanged>false</temporaryChanged>
<accessDriverType>oracle_loader</accessDriverType>
<rejectLimit></rejectLimit>
<columnProxies itemClass="oracle.dbtools.crest.model.design.storage.oracle.v12c.ColumnProxyOraclev12c">
<ColumnProxy name="RANGO_FOTOS" id="361F1225-2BC7-5E21-2B16-B2862C661C3D">
<createdBy>Usuario</createdBy>
<createdTime>2017-04-03 21:48:47 UTC</createdTime>
<ownerDesignName>disenoCubo</ownerDesignName>
</ColumnProxy>
<ColumnProxy name="FECHA_MODIFICACION" id="5E4A9691-2FC4-A52D-3E41-5DC51F14EDDA">
<createdBy>Usuario</createdBy>
<createdTime>2017-04-03 21:48:48 UTC</createdTime>
<ownerDesignName>disenoCubo</ownerDesignName>
</ColumnProxy>
<ColumnProxy name="ROCAS" id="6F1C7CA2-3BAB-82B9-31F6-1DD9E819D213">
<createdBy>Usuario</createdBy>
<createdTime>2017-04-03 21:48:47 UTC</createdTime>
<ownerDesignName>disenoCubo</ownerDesignName>
</ColumnProxy>
<ColumnProxy name="USUARIO_CREACION" id="801A6FD2-5677-0580-7536-16DB6B27FB2C">
<createdBy>Usuario</createdBy>
<createdTime>2017-04-03 21:48:48 UTC</createdTime>
<ownerDesignName>disenoCubo</ownerDesignName>
</ColumnProxy>
<ColumnProxy name="FECHA_CREACION" id="9C547C3C-787E-B350-2FC3-1D9D40BF49CF">
<createdBy>Usuario</createdBy>
<createdTime>2017-04-03 21:48:48 UTC</createdTime>
<ownerDesignName>disenoCubo</ownerDesignName>
</ColumnProxy>
<ColumnProxy name="SUBP_ID_SUBPARCELA" id="A4802D7F-A6CD-A27E-64B9-1FBDFF76BEA4">
<createdBy>Usuario</createdBy>
<createdTime>2017-04-03 21:48:47 UTC</createdTime>
<ownerDesignName>disenoCubo</ownerDesignName>
</ColumnProxy>
<ColumnProxy name="DISTACNCIA" id="AB801DC7-C0E6-FCE9-EB09-06EE3BC1AAC6">
<createdBy>Usuario</createdBy>
<createdTime>2017-04-03 21:48:47 UTC</createdTime>
<ownerDesignName>disenoCubo</ownerDesignName>
</ColumnProxy>
<ColumnProxy name="DENSIDAD" id="B1789B2F-25DA-0831-3E05-E73DF40AB138">
<createdBy>Usuario</createdBy>
<createdTime>2017-04-03 21:48:48 UTC</createdTime>
<ownerDesignName>disenoCubo</ownerDesignName>
</ColumnProxy>
<ColumnProxy name="RAICES" id="B6F6F3C5-E8DA-EF58-F745-977FF4E60A1C">
<createdBy>Usuario</createdBy>
<createdTime>2017-04-03 21:48:47 UTC</createdTime>
<ownerDesignName>disenoCubo</ownerDesignName>
</ColumnProxy>
<ColumnProxy name="CARBONO" id="BBC8163D-99F2-D84B-D00E-96C0482517D4">
<createdBy>Usuario</createdBy>
<createdTime>2017-04-03 21:48:47 UTC</createdTime>
<ownerDesignName>disenoCubo</ownerDesignName>
</ColumnProxy>
<ColumnProxy name="ID_SUELOS" id="D632F8C6-11C7-A742-0C52-F7A7B0D4AB33">
<createdBy>Usuario</createdBy>
<createdTime>2017-04-03 21:48:47 UTC</createdTime>
<ownerDesignName>disenoCubo</ownerDesignName>
</ColumnProxy>
<ColumnProxy name="FERTILIDAD" id="D7D1ADE8-F24C-43EB-F350-28DB9A3D349B">
<createdBy>Usuario</createdBy>
<createdTime>2017-04-03 21:48:47 UTC</createdTime>
<ownerDesignName>disenoCubo</ownerDesignName>
</ColumnProxy>
<ColumnProxy name="PESO_FRESCO" id="E605C864-FA3F-51B2-A74A-C0E1B0551D43">
<createdBy>Usuario</createdBy>
<createdTime>2017-04-03 21:48:48 UTC</createdTime>
<ownerDesignName>disenoCubo</ownerDesignName>
</ColumnProxy>
<ColumnProxy name="COLOR" id="EEC31E11-BE61-B37E-3C5A-CAB272006145">
<createdBy>Usuario</createdBy>
<createdTime>2017-04-03 21:48:47 UTC</createdTime>
<ownerDesignName>disenoCubo</ownerDesignName>
</ColumnProxy>
<ColumnProxy name="IFN_ID_BRIGADA_CONG" id="F2DC9608-F1B8-119B-7626-550D06C9A2EC">
<createdBy>Usuario</createdBy>
<createdTime>2017-04-03 23:13:36 UTC</createdTime>
<ownerDesignName>disenoCubo</ownerDesignName>
</ColumnProxy>
<ColumnProxy name="USUARIO_MODIFICACION" id="F454BC09-ADE5-0187-13BA-BB7C81477495">
<createdBy>Usuario</createdBy>
<createdTime>2017-04-03 21:48:48 UTC</createdTime>
<ownerDesignName>disenoCubo</ownerDesignName>
</ColumnProxy>
<ColumnProxy name="ORIENTACION" id="F4B500DB-079C-5256-2A1E-901E252EA311">
<createdBy>Usuario</createdBy>
<createdTime>2017-04-03 21:48:47 UTC</createdTime>
<ownerDesignName>disenoCubo</ownerDesignName>
</ColumnProxy>
</columnProxies>
<indexProxies>
<IndexProxy class="oracle.dbtools.crest.model.design.storage.oracle.v10g.IndexProxyOraclev10g" name="IFN_SUELOS_PK" id="75EB9399-5D3B-552E-0B45-2C6459BB728C">
<createdBy>Usuario</createdBy>
<createdTime>2017-04-03 21:48:48 UTC</createdTime>
<ownerDesignName>disenoCubo</ownerDesignName>
<schemaObject>3E48E386-25C0-F1B3-46F2-EE06203B5612</schemaObject>
<segment>E0F734DF-F388-32B1-6188-725BDBC7E430</segment>
<tableSpace>23A7666B-255B-EDE8-9B57-201EAD136BD1</tableSpace>
</IndexProxy>
</indexProxies>
<foreignKeys>
<ForeignKey class="oracle.dbtools.crest.model.design.storage.oracle.v10g.FKProxyOraclev10g" name="IFN_SLOS_IFN_BRIG_CONG_FK" id="49DFDD0E-6163-9487-6FB3-D13CA1DBE3FC">
<createdBy>Usuario</createdBy>
<createdTime>2017-04-03 23:13:36 UTC</createdTime>
<ownerDesignName>disenoCubo</ownerDesignName>
</ForeignKey>
<ForeignKey class="oracle.dbtools.crest.model.design.storage.oracle.v10g.FKProxyOraclev10g" name="IFN_SUELOS_IFN_SUBPARCELA_FK1" id="81DDD77A-827A-5866-97F9-98BCED1D69BA">
<createdBy>Usuario</createdBy>
<createdTime>2017-04-03 21:48:50 UTC</createdTime>
<ownerDesignName>disenoCubo</ownerDesignName>
</ForeignKey>
</foreignKeys>
<primaryKeys>
<PrimaryKey class="oracle.dbtools.crest.model.design.storage.oracle.v10g.PKProxyOraclev10g" name="IFN_SUELOS_PK" id="B7D53004-8A8C-DB1E-D48E-7A166D84F2DE">
<createdBy>Usuario</createdBy>
<createdTime>2017-04-03 21:48:49 UTC</createdTime>
<ownerDesignName>disenoCubo</ownerDesignName>
<segment>E0F734DF-F388-32B1-6188-725BDBC7E430</segment>
<tableSpace>23A7666B-255B-EDE8-9B57-201EAD136BD1</tableSpace>
<existingIndex>75EB9399-5D3B-552E-0B45-2C6459BB728C</existingIndex>
<indexSegment>E0F734DF-F388-32B1-6188-725BDBC7E430</indexSegment>
<indexSort>SORTED</indexSort>
<usingIndex>BY INDEX NAME</usingIndex>
</PrimaryKey>
</primaryKeys>
</TableProxyOraclev11g>